aoa_vis/gui.py
aoa_vis-0.1.0.dist-info/entry_points.txt
aoa_vis-0.1.0.dist-info/WHEEL
aoa_vis-0.1.0.dist-info/METADATA
aoa_vis-0.1.0.dist-info/RECORD
