Metadata-Version: 2.1
Name: aoa-vis
Version: 0.1.0
Summary: Angle of arrival visualisation.
License: MIT
Author: Sam Dudley
Author-email: dudley.co.uk@gmail.com
Requires-Python: >=3.8,<4.0
Classifier: License :: OSI Approved :: MIT License
Classifier: Programming Language :: Python :: 3
Classifier: Programming Language :: Python :: 3.8
Requires-Dist: numpy (>=1.19.4,<2.0.0)
Requires-Dist: scikit-learn (>=0.23.2,<0.24.0)
